package_zax_test/__init__.py
package_zax_test-0.1.1.dist-info/LICENSE
package_zax_test-0.1.1.dist-info/METADATA
package_zax_test-0.1.1.dist-info/WHEEL
package_zax_test-0.1.1.dist-info/top_level.txt
package_zax_test-0.1.1.dist-info/RECORD
